<?xml version="1.0" encoding="UTF-8"?>
<con:resource name="RegisterProduct" path="/IderaCoreServices/v1/Products/Register" id="f3ee5a6e-311d-4628-bcd8-80256a221fe9" xmlns:xsi="http://www.w3.org/2001/XMLSchema-instance" xmlns:con="http://eviware.com/soapui/config"><con:settings><con:setting id="f3ee5a6e-311d-4628-bcd8-80256a221fe9fileName">RegisterProduct</con:setting></con:settings><con:parameters/><con:method name="RegisterAProduct" id="31babaf7-fc7b-4ae4-a833-e54147489a03" method="POST"><con:settings/><con:parameters/><con:representation type="FAULT"><con:mediaType>application/xml; charset=utf-8</con:mediaType><con:status>403 400 500</con:status><con:params/><con:element>data</con:element></con:representation><con:representation type="REQUEST"><con:mediaType>application/json</con:mediaType><con:params/></con:representation><con:representation type="RESPONSE"><con:mediaType>application/json; charset=utf-8</con:mediaType><con:status>200</con:status><con:params/><con:element xmlns:reg="http://aut-sqlbi-118/IderaCoreServices/v1/Products/Register">reg:Response</con:element></con:representation><con:representation type="RESPONSE"><con:mediaType xsi:nil="true"/><con:status>0</con:status><con:params/><con:element>data</con:element></con:representation><con:representation type="RESPONSE"><con:mediaType xsi:nil="true"/><con:status>0</con:status><con:params/><con:element>data</con:element></con:representation><con:representation type="RESPONSE"><con:mediaType xsi:nil="true"/><con:status>0</con:status><con:params/><con:element>data</con:element></con:representation><con:representation type="RESPONSE"><con:mediaType xsi:nil="true"/><con:status>0</con:status><con:params/><con:element>data</con:element></con:representation><con:representation type="FAULT"><con:mediaType>text/html; charset=UTF-8</con:mediaType><con:status>405</con:status><con:params/><con:element>html</con:element></con:representation><con:representation type="RESPONSE"><con:mediaType xsi:nil="true"/><con:status>0</con:status><con:params/><con:element>data</con:element></con:representation><con:representation type="RESPONSE"><con:mediaType xsi:nil="true"/><con:status>0</con:status><con:params/><con:element>data</con:element></con:representation><con:request name="Register_A_Product" id="09201b71-1b77-4504-bb06-4b96f313a454" mediaType="application/json" postQueryString="false"><con:settings><con:setting id="com.eviware.soapui.impl.wsdl.WsdlRequest@request-headers">&lt;xml-fragment xmlns:con="http://eviware.com/soapui/config">
  &lt;con:entry key="Authorization" value="${#Project#CWF.Authorization}"/>
  &lt;con:entry key="Content-Type" value="application/json"/>
&lt;/xml-fragment></con:setting></con:settings><con:endpoint>http://${#Project#CWF.endpoint}</con:endpoint><con:request>{
	"DisplayName":"SampleProduct",
	"Host":"aut-sqlbi-118",
	"Name":"SampleProduct",
	"Password":"control*88",
	"Port": 9200,
	"User":"simpsons\\administrator",
	"Version":"1"
}</con:request><con:originalUri>http://aut-sqlbi-118/IderaCoreServices/v1/Products/Register</con:originalUri><con:credentials><con:username>Simpsons\administrator</con:username><con:password>control*88</con:password><con:domain>REDHOUSE</con:domain><con:selectedAuthProfile>Basic</con:selectedAuthProfile><con:addedBasicAuthenticationTypes>Basic</con:addedBasicAuthenticationTypes><con:authType>Global HTTP Settings</con:authType></con:credentials><con:jmsConfig JMSDeliveryMode="PERSISTENT"/><con:jmsPropertyConfig/><con:parameters/></con:request></con:method></con:resource>